CCankaoshouceDierBufen20171220/README.md
CCankaoshouceDierBufen20171220/__init__.py
CCankaoshouceDierBufen20171220/__main__.py
CCankaoshouceDierBufen20171220/file.epub
CCankaoshouceDierBufen20171220/index.html
CCankaoshouceDierBufen20171220/css/__init__.py
CCankaoshouceDierBufen20171220/css/annotations.css
CCankaoshouceDierBufen20171220/css/main.css
CCankaoshouceDierBufen20171220/css/normalize.css
CCankaoshouceDierBufen20171220/css/popup.css
CCankaoshouceDierBufen20171220/font/__init__.py
CCankaoshouceDierBufen20171220/font/fontello.eot
CCankaoshouceDierBufen20171220/font/fontello.svg
CCankaoshouceDierBufen20171220/font/fontello.ttf
CCankaoshouceDierBufen20171220/font/fontello.woff
CCankaoshouceDierBufen20171220/img/__init__.py
CCankaoshouceDierBufen20171220/img/annotator-glyph-sprite.png
CCankaoshouceDierBufen20171220/img/annotator-icon-sprite.png
CCankaoshouceDierBufen20171220/img/apple-touch-icon.png
CCankaoshouceDierBufen20171220/img/cancelfullscreen.png
CCankaoshouceDierBufen20171220/img/close.png
CCankaoshouceDierBufen20171220/img/fullscreen.png
CCankaoshouceDierBufen20171220/img/loader.gif
CCankaoshouceDierBufen20171220/img/menu-icon.png
CCankaoshouceDierBufen20171220/img/save.png
CCankaoshouceDierBufen20171220/img/saved.png
CCankaoshouceDierBufen20171220/img/settings-s.png
CCankaoshouceDierBufen20171220/img/settings.png
CCankaoshouceDierBufen20171220/img/star.png
CCankaoshouceDierBufen20171220/js/__init__.py
CCankaoshouceDierBufen20171220/js/epub.js
CCankaoshouceDierBufen20171220/js/epub.min.js
CCankaoshouceDierBufen20171220/js/epub.min.map
CCankaoshouceDierBufen20171220/js/hooks.min.js
CCankaoshouceDierBufen20171220/js/hooks.min.map
CCankaoshouceDierBufen20171220/js/reader.js
CCankaoshouceDierBufen20171220/js/reader.js.map
CCankaoshouceDierBufen20171220/js/reader.min.js
CCankaoshouceDierBufen20171220/js/reader.min.map
CCankaoshouceDierBufen20171220/js/hooks/__init__.py
CCankaoshouceDierBufen20171220/js/hooks/extensions/__init__.py
c_cankaoshouce_dier_bufen_2017_12_20-2024.3.1.0.dist-info/METADATA
c_cankaoshouce_dier_bufen_2017_12_20-2024.3.1.0.dist-info/WHEEL
c_cankaoshouce_dier_bufen_2017_12_20-2024.3.1.0.dist-info/entry_points.txt
c_cankaoshouce_dier_bufen_2017_12_20-2024.3.1.0.dist-info/top_level.txt
c_cankaoshouce_dier_bufen_2017_12_20-2024.3.1.0.dist-info/RECORD
